{"station": "\u5927\u82ac", "data": [{"time": 6, "in": 27.0, "out": 625.0}, {"time": 7, "in": 582.0, "out": 3987.0}, {"time": 8, "in": 758.0, "out": 4029.0}, {"time": 9, "in": 529.0, "out": 1373.0}, {"time": 10, "in": 570.0, "out": 881.0}, {"time": 11, "in": 524.0, "out": 740.0}, {"time": 12, "in": 631.0, "out": 725.0}, {"time": 13, "in": 583.0, "out": 867.0}, {"time": 14, "in": 722.0, "out": 887.0}, {"time": 15, "in": 783.0, "out": 739.0}, {"time": 16, "in": 927.0, "out": 692.0}, {"time": 17, "in": 1473.0, "out": 705.0}, {"time": 18, "in": 3657.0, "out": 999.0}, {"time": 19, "in": 3427.0, "out": 715.0}, {"time": 20, "in": 1625.0, "out": 523.0}, {"time": 21, "in": 1365.0, "out": 452.0}, {"time": 22, "in": 926.0, "out": 331.0}, {"time": 23, "in": 451.0, "out": 54.0}], "totalIn": 19560, "totalOut": 19324, "totalCnt": 38884}